mortar_import/__init__.py
mortar_import/diff.py
mortar_import/extractors.py
mortar_import/sqlalchemy.py
mortar_import/temporal.py
tests/__init__.py
tests/test_plain.py
tests/test_sqlalchemy.py
tests/test_temporal.py
mortar_import-0.12.1.dist-info/METADATA
mortar_import-0.12.1.dist-info/WHEEL
mortar_import-0.12.1.dist-info/top_level.txt
mortar_import-0.12.1.dist-info/RECORD
