Metadata-Version: 2.1
Name: mortar-import
Version: 0.12.1
Summary: Tools for importing data, particularly when using mortar_mixins
Home-page: https://github.com/Mortar/mortar_import
Author: Chris Withers
Author-email: chris@withers.org
License: MIT
Platform: UNKNOWN
Requires-Dist: six
Provides-Extra: build
Requires-Dist: setuptools-git ; extra == 'build'
Requires-Dist: wheel ; extra == 'build'
Requires-Dist: twine ; extra == 'build'
Provides-Extra: test
Requires-Dist: pytest ; extra == 'test'
Requires-Dist: pytest-cov ; extra == 'test'
Requires-Dist: testfixtures ; extra == 'test'
Requires-Dist: coveralls ; extra == 'test'
Requires-Dist: mortar-mixins ; extra == 'test'
Requires-Dist: mortar-rdb ; extra == 'test'
Requires-Dist: mock ; extra == 'test'
